[
  {
    "ContainingType": "DataGridSystem.Controllers.AuthController",
    "Method": "AdminsEndpoint",
    "RelativePath": "api/Auth/Admins",
    "HttpMethod": "GET",
    "IsController": true,
    "Order": 0,
    "Parameters": [],
    "ReturnTypes": []
  },
  {
    "ContainingType": "DataGridSystem.Controllers.AuthController",
    "Method": "AdminsAndUsersEndpoint",
    "RelativePath": "api/Auth/AdminsAndUsers",
    "HttpMethod": "GET",
    "IsController": true,
    "Order": 0,
    "Parameters": [],
    "ReturnTypes": []
  },
  {
    "ContainingType": "DataGridSystem.Controllers.AuthController",
    "Method": "Login",
    "RelativePath": "api/Auth/login",
    "HttpMethod": "POST",
    "IsController": true,
    "Order": 0,
    "Parameters": [
      {
        "Name": "login",
        "Type": "DataGridSystem.Controllers.LoginModel",
        "IsRequired": true
      }
    ],
    "ReturnTypes": []
  },
  {
    "ContainingType": "DataGridSystem.Controllers.AuthController",
    "Method": "PublicEndpoint",
    "RelativePath": "api/Auth/Public",
    "HttpMethod": "GET",
    "IsController": true,
    "Order": 0,
    "Parameters": [],
    "ReturnTypes": []
  },
  {
    "ContainingType": "DataGridSystem.Controllers.AuthController",
    "Method": "Register",
    "RelativePath": "api/Auth/register",
    "HttpMethod": "POST",
    "IsController": true,
    "Order": 0,
    "Parameters": [
      {
        "Name": "registerModel",
        "Type": "DataGridSystem.Models.RegisterModel",
        "IsRequired": true
      }
    ],
    "ReturnTypes": []
  },
  {
    "ContainingType": "DataGridSystem.Controllers.AuthController",
    "Method": "UsersEndpoint",
    "RelativePath": "api/Auth/Users",
    "HttpMethod": "GET",
    "IsController": true,
    "Order": 0,
    "Parameters": [],
    "ReturnTypes": []
  },
  {
    "ContainingType": "DataGridSystem.Controllers.ColumnsController",
    "Method": "CreateColumn",
    "RelativePath": "api/Columns",
    "HttpMethod": "POST",
    "IsController": true,
    "Order": 0,
    "Parameters": [
      {
        "Name": "column",
        "Type": "DataGridSystem.Models.Column",
        "IsRequired": true
      }
    ],
    "ReturnTypes": []
  },
  {
    "ContainingType": "DataGridSystem.Controllers.ColumnsController",
    "Method": "GetColumns",
    "RelativePath": "api/Columns/{gridId}",
    "HttpMethod": "GET",
    "IsController": true,
    "Order": 0,
    "Parameters": [
      {
        "Name": "gridId",
        "Type": "System.Int32",
        "IsRequired": true
      }
    ],
    "ReturnTypes": []
  },
  {
    "ContainingType": "DataGridSystem.Controllers.ColumnsController",
    "Method": "GetColumn",
    "RelativePath": "api/Columns/{id}",
    "HttpMethod": "GET",
    "IsController": true,
    "Order": 0,
    "Parameters": [
      {
        "Name": "id",
        "Type": "System.Int32",
        "IsRequired": true
      }
    ],
    "ReturnTypes": []
  },
  {
    "ContainingType": "DataGridSystem.Controllers.ColumnsController",
    "Method": "UpdateColumn",
    "RelativePath": "api/Columns/{id}",
    "HttpMethod": "PUT",
    "IsController": true,
    "Order": 0,
    "Parameters": [
      {
        "Name": "id",
        "Type": "System.Int32",
        "IsRequired": true
      },
      {
        "Name": "updatedColumn",
        "Type": "DataGridSystem.Models.Column",
        "IsRequired": true
      }
    ],
    "ReturnTypes": []
  },
  {
    "ContainingType": "DataGridSystem.Controllers.ColumnsController",
    "Method": "DeleteColumn",
    "RelativePath": "api/Columns/{id}",
    "HttpMethod": "DELETE",
    "IsController": true,
    "Order": 0,
    "Parameters": [
      {
        "Name": "id",
        "Type": "System.Int32",
        "IsRequired": true
      }
    ],
    "ReturnTypes": []
  },
  {
    "ContainingType": "DataGridSystem.Controllers.DataGridsController",
    "Method": "GetDataGrids",
    "RelativePath": "api/DataGrids",
    "HttpMethod": "GET",
    "IsController": true,
    "Order": 0,
    "Parameters": [],
    "ReturnTypes": []
  },
  {
    "ContainingType": "DataGridSystem.Controllers.DataGridsController",
    "Method": "CreateDataGrid",
    "RelativePath": "api/DataGrids",
    "HttpMethod": "POST",
    "IsController": true,
    "Order": 0,
    "Parameters": [
      {
        "Name": "dataGridDto",
        "Type": "DataGridSystem.DTOs.DataGridDto",
        "IsRequired": true
      }
    ],
    "ReturnTypes": []
  },
  {
    "ContainingType": "DataGridSystem.Controllers.DataGridsController",
    "Method": "GetDataGrid",
    "RelativePath": "api/DataGrids/{id}",
    "HttpMethod": "GET",
    "IsController": true,
    "Order": 0,
    "Parameters": [
      {
        "Name": "id",
        "Type": "System.Int32",
        "IsRequired": true
      }
    ],
    "ReturnTypes": []
  },
  {
    "ContainingType": "DataGridSystem.Controllers.DataGridsController",
    "Method": "UpdateDataGrid",
    "RelativePath": "api/DataGrids/{id}",
    "HttpMethod": "PUT",
    "IsController": true,
    "Order": 0,
    "Parameters": [
      {
        "Name": "id",
        "Type": "System.Int32",
        "IsRequired": true
      },
      {
        "Name": "dataGridDto",
        "Type": "DataGridSystem.DTOs.DataGridDto",
        "IsRequired": true
      }
    ],
    "ReturnTypes": []
  },
  {
    "ContainingType": "DataGridSystem.Controllers.DataGridsController",
    "Method": "DeleteDataGrid",
    "RelativePath": "api/DataGrids/{id}",
    "HttpMethod": "DELETE",
    "IsController": true,
    "Order": 0,
    "Parameters": [
      {
        "Name": "id",
        "Type": "System.Int32",
        "IsRequired": true
      }
    ],
    "ReturnTypes": []
  },
  {
    "ContainingType": "DataGridSystem.Controllers.HomeController",
    "Method": "Index",
    "RelativePath": "api/Home",
    "HttpMethod": "GET",
    "IsController": true,
    "Order": 0,
    "Parameters": [],
    "ReturnTypes": []
  },
  {
    "ContainingType": "DataGridSystem.Controllers.RowsController",
    "Method": "CreateRow",
    "RelativePath": "api/Rows",
    "HttpMethod": "POST",
    "IsController": true,
    "Order": 0,
    "Parameters": [
      {
        "Name": "row",
        "Type": "DataGridSystem.Models.Row",
        "IsRequired": true
      }
    ],
    "ReturnTypes": []
  },
  {
    "ContainingType": "DataGridSystem.Controllers.RowsController",
    "Method": "GetRows",
    "RelativePath": "api/Rows/{gridId}",
    "HttpMethod": "GET",
    "IsController": true,
    "Order": 0,
    "Parameters": [
      {
        "Name": "gridId",
        "Type": "System.Int32",
        "IsRequired": true
      }
    ],
    "ReturnTypes": []
  },
  {
    "ContainingType": "DataGridSystem.Controllers.RowsController",
    "Method": "UpdateRow",
    "RelativePath": "api/Rows/{id}",
    "HttpMethod": "PUT",
    "IsController": true,
    "Order": 0,
    "Parameters": [
      {
        "Name": "id",
        "Type": "System.Int32",
        "IsRequired": true
      },
      {
        "Name": "updatedRow",
        "Type": "DataGridSystem.Models.Row",
        "IsRequired": true
      }
    ],
    "ReturnTypes": []
  },
  {
    "ContainingType": "DataGridSystem.Controllers.RowsController",
    "Method": "DeleteRow",
    "RelativePath": "api/Rows/{id}",
    "HttpMethod": "DELETE",
    "IsController": true,
    "Order": 0,
    "Parameters": [
      {
        "Name": "id",
        "Type": "System.Int32",
        "IsRequired": true
      }
    ],
    "ReturnTypes": []
  },
  {
    "ContainingType": "DataGridSystem.Controllers.RowsController",
    "Method": "DeleteRows",
    "RelativePath": "api/Rows/batch",
    "HttpMethod": "DELETE",
    "IsController": true,
    "Order": 0,
    "Parameters": [
      {
        "Name": "rowIds",
        "Type": "System.Int32[]",
        "IsRequired": true
      }
    ],
    "ReturnTypes": []
  },
  {
    "ContainingType": "DataGridSystem.Controllers.RowsController",
    "Method": "CopyPasteRows",
    "RelativePath": "api/Rows/copy-paste",
    "HttpMethod": "POST",
    "IsController": true,
    "Order": 0,
    "Parameters": [
      {
        "Name": "request",
        "Type": "DataGridSystem.Controllers.CopyPasteRequest",
        "IsRequired": true
      }
    ],
    "ReturnTypes": []
  },
  {
    "ContainingType": "DataGridSystem.Controllers.SomeSecureController",
    "Method": "GetSecureData",
    "RelativePath": "api/SomeSecure/secure-data",
    "HttpMethod": "GET",
    "IsController": true,
    "Order": 0,
    "Parameters": [],
    "ReturnTypes": []
  }
]